laser_at.py
circuitpython_laser_at-0.9.0.dist-info/LICENSE
circuitpython_laser_at-0.9.0.dist-info/METADATA
circuitpython_laser_at-0.9.0.dist-info/WHEEL
circuitpython_laser_at-0.9.0.dist-info/top_level.txt
circuitpython_laser_at-0.9.0.dist-info/RECORD
