Metadata-Version: 2.1
Name: circuitpython-laser-at
Version: 0.9.0
Summary: Driver for an inexpensive laser rangefinder module, made by AT, available on aliexpress.
Author-email: Adafruit Industries <circuitpython@adafruit.com>
License: MIT
Project-URL: Homepage, https://github.com/furbrain/CircuitPython_laser_at
Keywords: adafruit,blinka,circuitpython,micropython,laser_at,rangefinder,laser,distance,disto
Classifier: Intended Audience :: Developers
Classifier: Topic :: Software Development :: Libraries
Classifier: Topic :: Software Development :: Embedded Systems
Classifier: Topic :: System :: Hardware
Classifier: License :: OSI Approved :: MIT License
Classifier: Programming Language :: Python :: 3
License-File: LICENSE
Requires-Dist: Adafruit-Blinka
Provides-Extra: optional
